{
  "title": "The Far Side",
  "subtitle": "RSS feed for daily The Far Side comics. Copyright FarWorks, Inc. All rights reserved.",
  "link": "https://www.thefarside.com/",
  "id": "https://www.thefarside.com/",
  "updated": "2024-10-22T15:19:48Z",
  "author": "Gary Larson",
  "entries": [
    {
      "title": "The Far Side comic 1 for October 22, 2024",
      "link": "https://www.thefarside.com/2024/10/22",
      "updated": "2024-10-22T15:19:48Z",
      "id": "https://www.thefarside.com/2024/10/22",
      "summary": {
        "img": "https://assets.amuniversal.com/6087dd50d7420137c8a6005056a9545d",
        "caption": "\n    “And I like honesty in a relationship—I’m not into playing games.”\n  ",
        "link": "https://www.thefarside.com/2024/10/22/0"
      }
    },
    {
      "title": "The Far Side comic 2 for October 22, 2024",
      "link": "https://www.thefarside.com/2024/10/22",
      "updated": "2024-10-22T15:19:48Z",
      "id": "https://www.thefarside.com/2024/10/22",
      "summary": {
        "img": "https://assets.amuniversal.com/61c4d960d1ad0137c697005056a9545d",
        "caption": "\n    “Professor LaVonne had many enemies in the entomological world, detective, but if you examine that data label, you’ll find exactly when and where he was—shall we say—‘collected.’”\n  ",
        "link": "https://www.thefarside.com/2024/10/22/1"
      }
    },
    {
      "title": "The Far Side comic 3 for October 22, 2024",
      "link": "https://www.thefarside.com/2024/10/22",
      "updated": "2024-10-22T15:19:48Z",
      "id": "https://www.thefarside.com/2024/10/22",
      "summary": {
        "img": "https://assets.amuniversal.com/7c761210e9ee0137cf93005056a9545d",
        "caption": "\n    How attack-wiener dogs are trained\n  ",
        "link": "https://www.thefarside.com/2024/10/22/2"
      }
    },
    {
      "title": "The Far Side comic 4 for October 22, 2024",
      "link": "https://www.thefarside.com/2024/10/22",
      "updated": "2024-10-22T15:19:48Z",
      "id": "https://www.thefarside.com/2024/10/22",
      "summary": {
        "img": "https://assets.amuniversal.com/60401050d8ba0137c959005056a9545d",
        "caption": "\n    Animal lures\n  ",
        "link": "https://www.thefarside.com/2024/10/22/3"
      }
    },
    {
      "title": "The Far Side comic 5 for October 22, 2024",
      "link": "https://www.thefarside.com/2024/10/22",
      "updated": "2024-10-22T15:19:48Z",
      "id": "https://www.thefarside.com/2024/10/22",
      "summary": {
        "img": "https://assets.amuniversal.com/abae2850df110137cbaf005056a9545d",
        "caption": "\n    The 100-meter mosey\n  ",
        "link": "https://www.thefarside.com/2024/10/22/4"
      }
    }
  ]
}